{
  "execution_id": "d9abbd48-9730-4086-92c8-56ecaffebb39",
  "timestamp": "2025-08-10T22:54:34.768938",
  "flowchart_name": "simple2",
  "execution_data": {
    "status": "failed",
    "execution_order": [
      1754557300491.1255,
      1754862315571.3855,
      1754646735053.426,
      1754853828832.737,
      1754592052289.3586,
      1754592498999.7505,
      1754593440510.8223,
      1754843101576.906,
      1754593440044.931,
      1754485128247.5793,
      1754849299897.9001,
      1754850114255.0886
    ],
    "results": [
      {
        "node_id": 1754557300491.1255,
        "node_name": "assign variable + sqaure",
        "python_file": "nodes/example.py",
        "success": true,
        "output": "Enter a number: 3\nEnter a number: 4\n9.0",
        "error": null,
        "runtime": 2125,
        "timestamp": "22:54:34",
        "return_value": 9,
        "function_name": "get_user_input"
      },
      {
        "node_id": 1754862315571.3855,
        "node_name": "variableC",
        "python_file": "",
        "success": false,
        "output": "",
        "error": "node_id and python_file are required",
        "runtime": 18,
        "timestamp": "22:54:34",
        "return_value": null
      }
    ],
    "total_nodes": 12,
    "successful_nodes": 1,
    "error_message": "execution stopped at node: variableC",
    "flowchart_state": {
      "nodes": [
        {
          "id": 1754485128247.5793,
          "name": "node 3",
          "x": 605.8889465332031,
          "y": 282.6341857910156,
          "pythonFile": "nodes/node3.py",
          "description": "",
          "type": "python_file"
        },
        {
          "id": 1754557300491.1255,
          "name": "assign variable + sqaure",
          "x": 819.2770385742188,
          "y": -311.13140869140625,
          "pythonFile": "nodes/example.py",
          "description": "",
          "type": "python_file"
        },
        {
          "id": 1754557341635.2678,
          "name": "Input Node",
          "x": 453.612548828125,
          "y": -311.5063371658325,
          "pythonFile": "nodes/example.py",
          "description": "input parameters",
          "type": "input_node"
        },
        {
          "id": 1754592052289.3586,
          "name": "girl boy?",
          "x": 811.1217041015625,
          "y": -74.94430541992188,
          "pythonFile": "",
          "description": "",
          "type": "if_node"
        },
        {
          "id": 1754592498999.7505,
          "name": "python node",
          "x": 1194.6910400390625,
          "y": 135.51309204101562,
          "pythonFile": "",
          "description": "",
          "type": "python_file"
        },
        {
          "id": 1754593440044.931,
          "name": "python node",
          "x": 1442,
          "y": 235,
          "pythonFile": "",
          "description": "",
          "type": "python_file"
        },
        {
          "id": 1754593440510.8223,
          "name": "python node",
          "x": 1448,
          "y": 102,
          "pythonFile": "",
          "description": "",
          "type": "python_file"
        },
        {
          "id": 1754646735053.426,
          "name": "python node",
          "x": 811.1217041015625,
          "y": -154.94430541992188,
          "pythonFile": "nodes/node1.py",
          "description": "",
          "type": "python_file"
        },
        {
          "id": 1754646773379.522,
          "name": "Input Node",
          "x": 486.8837585449219,
          "y": -100.53401947021484,
          "pythonFile": "nodes/node1.py",
          "description": "input parameters",
          "type": "input_node"
        },
        {
          "id": 1754843101576.906,
          "name": "python node",
          "x": 915.9024658203125,
          "y": 210.162109375,
          "pythonFile": "",
          "description": "",
          "type": "python_file"
        },
        {
          "id": 1754849299897.9001,
          "name": "python node",
          "x": 862.0789184570312,
          "y": 383.677490234375,
          "pythonFile": "",
          "description": "",
          "type": "python_file"
        },
        {
          "id": 1754850114255.0886,
          "name": "if condition",
          "x": 862.0789184570312,
          "y": 463.677490234375,
          "pythonFile": "",
          "description": "",
          "type": "if_node"
        },
        {
          "id": 1754853828832.737,
          "name": "result",
          "x": 688.5722379005184,
          "y": -232.65509209861293,
          "pythonFile": "",
          "description": "",
          "type": "data_save"
        },
        {
          "id": 1754862315571.3855,
          "name": "variableC",
          "x": 1052.6401158892168,
          "y": -360.4450514586955,
          "pythonFile": "",
          "description": "",
          "type": "data_save"
        }
      ],
      "links": [
        {
          "selectable": false,
          "source": 1754557341635.2678,
          "style": "dashed",
          "target": 1754557300491.1255,
          "type": "input_connection"
        },
        {
          "source": 1754592052289.3586,
          "target": 1754485128247.5793
        },
        {
          "conditions": [
            {
              "operator": "==",
              "value": "",
              "variable": "result"
            }
          ],
          "source": 1754592052289.3586,
          "target": 1754592498999.7505
        },
        {
          "source": 1754592498999.7505,
          "target": 1754593440510.8223
        },
        {
          "source": 1754592498999.7505,
          "target": 1754593440044.931
        },
        {
          "source": 1754557300491.1255,
          "target": 1754646735053.426
        },
        {
          "selectable": false,
          "source": 1754646773379.522,
          "style": "dashed",
          "target": 1754646735053.426,
          "type": "input_connection"
        },
        {
          "source": 1754592052289.3586,
          "target": 1754843101576.906
        },
        {
          "source": 1754646735053.426,
          "target": 1754592052289.3586
        },
        {
          "selectable": false,
          "source": 1754849299897.9001,
          "target": 1754850114255.0886
        },
        {
          "selectable": false,
          "source": 1754646735053.426,
          "style": "dashed",
          "target": 1754853828832.737
        },
        {
          "selectable": false,
          "source": 1754557300491.1255,
          "style": "dashed",
          "target": 1754862315571.3855
        }
      ],
      "groups": [
        {
          "description": "",
          "id": 1754608357871.8955,
          "name": "final",
          "nodeIds": [
            1754592498999.7505,
            1754593440510.8223,
            1754593440044.931
          ]
        }
      ]
    }
  }
}